README
setup.py
pymodem/__init__.py
pymodem/chat.py
pymodem/cli.py
pymodem/gsm_03_38.py
pymodem/hexbuffer.py
pymodem/modem.py
pymodem/sms.py
pymodem.egg-info/PKG-INFO
pymodem.egg-info/SOURCES.txt
pymodem.egg-info/dependency_links.txt
pymodem.egg-info/top_level.txt